stodynprog/__init__.py
stodynprog/stodynprog.py
stodynprog/dolointerpolation/__init__.py
stodynprog/dolointerpolation/multilinear.py
stodynprog/dolointerpolation/multilinear_cython.pyd
stodynprog/tests/__init__.py
stodynprog/tests/test_dolointerp.py
stodynprog/tests/test_stodynprog.py
stodynprog-0.1.1.dist-info/DESCRIPTION.rst
stodynprog-0.1.1.dist-info/METADATA
stodynprog-0.1.1.dist-info/RECORD
stodynprog-0.1.1.dist-info/WHEEL
stodynprog-0.1.1.dist-info/metadata.json
stodynprog-0.1.1.dist-info/top_level.txt
