Metadata-Version: 2.0
Name: stodynprog
Version: 0.1.1
Summary: a library for solving stochastic optimal control problems, also called dynamic optimization
Home-page: https://github.com/pierre-haessig/stodynprog
Author: Pierre Haessig
Author-email: pierre.haessig@crans.org
License: BSD-3
Platform: UNKNOWN
Classifier: Development Status :: 4 - Beta
Classifier: Intended Audience :: Science/Research
Classifier: Topic :: Software Development :: Build Tools
Classifier: License :: OSI Approved :: BSD License
Classifier: Programming Language :: Python :: 2
Classifier: Programming Language :: Python :: 2.6
Classifier: Programming Language :: Python :: 2.7
Requires-Dist: cython
Requires-Dist: numpy
Requires-Dist: scipy
Provides-Extra: plots
Requires-Dist: matplotlib; extra == 'plots'
